myccli/__init__.py
myccli/__main__.py
myccli/compiler.py
myccli/config.py
myccli/main.py
myccli/packager.py
myccli/platform.py
myccli/poetry.py
myccli/scanner.py
myccli/terraform/__init__.py
myccli/terraform/common.py
myccli/terraform/provider.py
myccli/terraform/resources/__init__.py
myccli/terraform/resources/aws.py
myccli/terraform/resources/base.py
myccli/terraform/resources/docker.py
myccli/terraform/resources/null.py
myccli/terraform/writer.py
myccli-0.1.4.dist-info/entry_points.txt
myccli-0.1.4.dist-info/WHEEL
myccli-0.1.4.dist-info/METADATA
myccli-0.1.4.dist-info/RECORD
