Metadata-Version: 2.1
Name: myccli
Version: 0.1.4
Summary: Mycelium CLI
Home-page: https://github.com/BizarreCake/myccli
License: MIT
Author: Jacob Zhitomirsky
Author-email: bizarrecake@gmail.com
Requires-Python: >=3.9,<4.0
Classifier: License :: OSI Approved :: MIT License
Classifier: Programming Language :: Python :: 3
Classifier: Programming Language :: Python :: 3.9
Classifier: Programming Language :: Python :: 3.10
Requires-Dist: boto3 (>=1.24.70,<2.0.0)
Requires-Dist: dnspython (>=2.2.1,<3.0.0)
Requires-Dist: myc (>=0.1.2,<0.2.0)
Requires-Dist: requests (>=2.28.1,<3.0.0)
Requires-Dist: toml (>=0.10.2,<0.11.0)
Requires-Dist: typer[all] (>=0.6.1,<0.7.0)
Project-URL: Repository, https://github.com/BizarreCake/myccli
